phonexia_deepfake_detection_client.py
phonexia_deepfake_detection_client-4.0.1.dist-info/METADATA
phonexia_deepfake_detection_client-4.0.1.dist-info/WHEEL
phonexia_deepfake_detection_client-4.0.1.dist-info/entry_points.txt
phonexia_deepfake_detection_client-4.0.1.dist-info/top_level.txt
phonexia_deepfake_detection_client-4.0.1.dist-info/RECORD
